multiqc_cgs/__init__.py
multiqc_cgs/hooks.py
multiqc_cgs-1.0.0.dist-info/LICENSE.md
multiqc_cgs-1.0.0.dist-info/METADATA
multiqc_cgs-1.0.0.dist-info/WHEEL
multiqc_cgs-1.0.0.dist-info/entry_points.txt
multiqc_cgs-1.0.0.dist-info/top_level.txt
multiqc_cgs-1.0.0.dist-info/RECORD
